{
  "_format": "hh-sol-cache-2",
  "files": {
    "/Users/mudasirasultana/Documents/SentinelChain/contracts/Lock.sol": {
      "lastModificationDate": 1744088121200,
      "contentHash": "7eee587c347fe6b1de50c96688cb9477",
      "sourceName": "contracts/Lock.sol",
      "solcConfig": {
        "version": "0.8.28",
        "settings": {
          "evmVersion": "paris",
          "optimizer": {
            "enabled": false,
            "runs": 200
          },
          "outputSelection": {
            "*": {
              "*": [
                "abi",
                "evm.bytecode",
                "evm.deployedBytecode",
                "evm.methodIdentifiers",
                "metadata"
              ],
              "": [
                "ast"
              ]
            }
          }
        }
      },
      "imports": [],
      "versionPragmas": [
        "^0.8.28"
      ],
      "artifacts": [
        "Lock"
      ]
    },
    "/Users/mudasirasultana/Documents/SentinelChain/contracts/SentinelChain.sol": {
      "lastModificationDate": 1746965192729,
      "contentHash": "34bfb77283e11bf90291ade6733351ee",
      "sourceName": "contracts/SentinelChain.sol",
      "solcConfig": {
        "version": "0.8.28",
        "settings": {
          "evmVersion": "paris",
          "optimizer": {
            "enabled": false,
            "runs": 200
          },
          "outputSelection": {
            "*": {
              "*": [
                "abi",
                "evm.bytecode",
                "evm.deployedBytecode",
                "evm.methodIdentifiers",
                "metadata"
              ],
              "": [
                "ast"
              ]
            }
          }
        }
      },
      "imports": [],
      "versionPragmas": [
        "^0.8.0"
      ],
      "artifacts": [
        "SentinelChain"
      ]
    }
  }
}
